{"addonId": "ReminderApp", "displayName": "Erinnerungen", "URL": "https://raw.githubusercontent.com/Adriano-Barbieri62/ReminderApp-Addon/main/ReminderApp-2.8.nvda-addon", "description": "Dieses Add-on wurde entwickelt, um Erinnerungen, Termine, Jahrestage und Geburtstage auf originelle und intuitive Weise zu verwalten.\nMit ReminderApp k\u00f6nnen Sie nicht nur Ihre Erinnerungen erstellen und organisieren, sondern haben auch ein Adressbuch f\u00fcr Ihre Kontakte zur Hand.\nNVDA+Shift+F1, Stoppt den laufenden Alarm.\nNVDA+Shift+F2, \u00d6ffnet die ReminderApp-Oberfl\u00e4che, bei zweimaligem Dr\u00fccken wird sie geschlossen.\nNVDA+Shift+F3, Zeigt eine Vorschau der heutigen Erinnerungen, bei erneutem Dr\u00fccken wird sie geschlossen.\nF\u00fcr weitere Anweisungen k\u00f6nnen Sie im Add-on-Manager auch die Schaltfl\u00e4che \u201eAdd-on-Hilfe\u201c dr\u00fccken.", "sha256": "b405d5af0ad75928eccd99b24267beea86dcbe843e4c4b002a7400604f0ca6ef", "addonVersionName": "2.8", "addonVersionNumber": {"major": 2, "minor": 8, "patch": 0}, "minNVDAVersion": {"major": 2020, "minor": 1, "patch": 0}, "lastTestedVersion": {"major": 2026, "minor": 1, "patch": 0}, "channel": "stable", "publisher": "Adriano Barbieri", "sourceURL": "https://github.com/Adriano-Barbieri62/ReminderApp-Addon", "license": "GPL v2", "homepage": "https://github.com/Adriano-Barbieri62/ReminderApp-Addon", "licenseURL": "https://www.gnu.org/licenses/gpl-2.0.html", "submissionTime": 1782582547000, "vtScanUrl": "https://www.virustotal.com/gui/file/b405d5af0ad75928eccd99b24267beea86dcbe843e4c4b002a7400604f0ca6ef", "scanResults": {"virusTotal": [{"_id": "b405d5af0ad75928eccd99b24267beea86dcbe843e4c4b002a7400604f0ca6ef", "_type": "file", "filecondis": {"dhash": "0000000006070400", "raw_md5": "25070908243751d7bb43c1b80181600b"}, "first_submission_date": 1782582553, "last_analysis_results": {}, "last_analysis_stats": {"confirmed-timeout": 0, "failure": 0, "harmless": 0, "malicious": 0, "suspicious": 0, "timeout": 0, "type-unsupported": 0, "undetected": 0}, "last_modification_date": 1782582554, "last_submission_date": 1782582553, "md5": "fcb9f257a88ac0948d1af2dd3f516cc4", "names": [], "reputation": 0, "sha1": "ccf3b93f7f1c696dd42cf632c5597909c3416d5f", "sha256": "b405d5af0ad75928eccd99b24267beea86dcbe843e4c4b002a7400604f0ca6ef", "size": 10337545, "tags": [], "times_submitted": 1, "total_votes": {"harmless": 0, "malicious": 0}, "type_description": "unknown", "type_tags": [], "unique_sources": 1}]}, "reviewUrl": "https://github.com/nvaccess/addon-datastore/discussions/5034"}