{"addonId": "simpleCopy", "displayName": "simpleCopy", "URL": "https://github.com/chaichaimee/simpleCopy/releases/download/2026.7.7/simpleCopy-v2026.7.7.nvda-addon", "description": "Kekuatan Tangkapan Utama: URL, Teks, Kata-kata Terakhir yang Diucapkan; Semua ada di ujung jari Anda, Lebih Cepat dan Lebih Cerdas\nTombol Pintas:\nCTRL+Shift+A\nKetukan Tunggal: Salin URL\n Ketukan Ganda: Salin Tautan Hiper\nCTRL+Shift+V\nKetukan Tunggal: Salin dan Tambahkan teks\n Ketukan Ganda: Salin dari Kursor Peninjau\nKetukan Tiga Kali: Bersihkan papan klip\nF9\nKetukan Tunggal: Salin Ucapan Terakhir\nKetukan Ganda: Tambahkan Ucapan Terakhir\nKetukan Tiga Kali: Salin Hingga Ucapan Terakhir\nShift+F9\nKetukan Tunggal: Navigasi ke item riwayat ucapan sebelumnya\nKetukan Ganda: Navigasi ke item riwayat ucapan berikutnya\nKetukan Tiga Kali: Buka Berkas Riwayat Rekaman Ucapan", "sha256": "013734fb9e520b6735e40db3e31c8afda1f8e78bcf6fbc731accf7b3add5f4cd", "addonVersionName": "2026.7.7", "addonVersionNumber": {"major": 2026, "minor": 7, "patch": 7}, "minNVDAVersion": {"major": 2024, "minor": 4, "patch": 0}, "lastTestedVersion": {"major": 2026, "minor": 1, "patch": 1}, "channel": "stable", "publisher": "Chai Chaimee", "sourceURL": "https://github.com/chaichaimee/simpleCopy", "license": "GPL v2", "homepage": "https://github.com/chaichaimee/simpleCopy", "changelog": "Fixed an issue where triple-tap speech history inserted blank lines between captured speech entries; now entries are concatenated directly with newline only.", "licenseURL": "https://www.gnu.org/licenses/gpl-2.0.html", "submissionTime": 1784028710000, "vtScanUrl": "https://www.virustotal.com/gui/file/013734fb9e520b6735e40db3e31c8afda1f8e78bcf6fbc731accf7b3add5f4cd", "scanResults": {"virusTotal": [{"_id": "013734fb9e520b6735e40db3e31c8afda1f8e78bcf6fbc731accf7b3add5f4cd", "_type": "file", "filecondis": {"dhash": "00001c1c1d180000", "raw_md5": "9c1f1ee02edb9066eb3e8bd9a2d1d2d3"}, "first_submission_date": 1784028714, "last_analysis_results": {}, "last_analysis_stats": {"confirmed-timeout": 0, "failure": 0, "harmless": 0, "malicious": 0, "suspicious": 0, "timeout": 0, "type-unsupported": 0, "undetected": 0}, "last_modification_date": 1784028715, "last_submission_date": 1784028714, "md5": "7cfeb3bba4a8199c822cc340464641f1", "names": [], "reputation": 0, "sha1": "e3f83ab09b32a91e7e2295ce64a6102e4bd92083", "sha256": "013734fb9e520b6735e40db3e31c8afda1f8e78bcf6fbc731accf7b3add5f4cd", "size": 188824, "tags": [], "times_submitted": 1, "total_votes": {"harmless": 0, "malicious": 0}, "type_description": "unknown", "type_tags": [], "unique_sources": 1}]}, "reviewUrl": "https://github.com/nvaccess/addon-datastore/discussions/5972"}